<ns0:DataModelInfo xmlns:ns0="http://schemas.qualisystems.com/ResourceManagement/DataModelSchema.xsd">
  <ns0:Attributes>
    <ns0:AttributeInfo DefaultValue="" Description="Attribute description" IsReadOnly="false" Name="Attribute Name" Type="String">
      <ns0:Rules>
        <ns0:Rule Name="Configuration" />
        <ns0:Rule Name="Setting" />
      </ns0:Rules>
    </ns0:AttributeInfo>
  </ns0:Attributes>
  <ns0:ResourceFamilies>
    <ns0:ResourceFamily Description="" IsAdminOnly="true" IsSearchable="true" Name="Family Name">
      <ns0:AttachedAttributes />
      <ns0:AttributeValues />
      <ns0:Models>
        <ns0:ResourceModel Description="" ImagePath="vCenter_Model.png" Name="VMware vCenter" SupportsConcurrentCommands="true">
          <ns0:AttachedAttributes>
            <ns0:AttachedAttribute IsLocal="true" IsOverridable="true" Name="Attribute Name">
              <ns0:AllowedValues />
            </ns0:AttachedAttribute>
          </ns0:AttachedAttributes>
          <ns0:AttributeValues>
            <ns0:AttributeValue Name="Attribute Name" Value="Default Value" />
          </ns0:AttributeValues>
          <ns0:ParentModels />
          <ns0:Drivers>
            <ns0:DriverName>Driver Name</ns0:DriverName>
          </ns0:Drivers>
          <ns0:Scripts>
          </ns0:Scripts>
        </ns0:ResourceModel>
      </ns0:Models>
      <ns0:Categories />
    </ns0:ResourceFamily>
  </ns0:ResourceFamilies>
  <ns0:DriverDescriptors>
    <ns0:DriverDescriptor DriverType="PythonDriver" Name="Driver Name" />
  </ns0:DriverDescriptors>
  <ns0:ScriptDescriptors>
  </ns0:ScriptDescriptors>
</ns0:DataModelInfo>